_solib_k8/_U_S_Stensorflow_Uplugin_Czen_Ulibs_Ulinux___Uexternal_Samd_Ublis/libblis-mt.so.5
_solib_k8/_U_S_Stensorflow_Uplugin_Czen_Ulibs_Ulinux___Uexternal_Sllvm_Uopenmp/libiomp5.so
_solib_k8/_U_S_Stensorflow_Uplugin_Czen_Ulibs_Ulinux___Uexternal_Szen_Udnn/libamdZenDNN.so
my_plugin_dir/__init__.py
my_plugin_dir/python/__init__.py
my_plugin_dir/python/test.py
tensorflow-plugins/__init__.py
tensorflow-plugins/libamdcpu_plugin.so
zentf-5.1.0.dist-info/METADATA
zentf-5.1.0.dist-info/WHEEL
zentf-5.1.0.dist-info/top_level.txt
zentf-5.1.0.dist-info/RECORD
