Metadata-Version: 2.4
Name: zentf
Version: 5.1.0
Summary: zenTF : A TensorFlow extension for AMD EPYC CPUs.
Home-page: https://developer.amd.com/zendnn
Author: AMD
Author-email: zendnn.maintainers@amd.com
License: Apache 2.0
Keywords: tensorflow tensor machine learning plugin ZenDNN AMD
Classifier: Development Status :: 5 - Production/Stable
Classifier: Intended Audience :: Developers
Classifier: Intended Audience :: Education
Classifier: Intended Audience :: Science/Research
Classifier: License :: OSI Approved :: Apache Software License
Classifier: Programming Language :: Python :: 3
Classifier: Programming Language :: Python :: 3.9
Classifier: Programming Language :: Python :: 3.10
Classifier: Programming Language :: Python :: 3.11
Classifier: Programming Language :: Python :: 3.12
Classifier: Topic :: Scientific/Engineering
Classifier: Topic :: Scientific/Engineering :: Mathematics
Classifier: Topic :: Scientific/Engineering :: Artificial Intelligence
Classifier: Topic :: Software Development
Classifier: Topic :: Software Development :: Libraries
Classifier: Topic :: Software Development :: Libraries :: Python Modules
Requires-Dist: grpcio>=1.8.6
Requires-Dist: numpy==1.26.4
Requires-Dist: wheel>=0.26
Dynamic: author
Dynamic: author-email
Dynamic: classifier
Dynamic: description
Dynamic: description-content-type
Dynamic: home-page
Dynamic: keywords
Dynamic: license
Dynamic: requires-dist
Dynamic: summary
